Metadata-Version: 1.0
Name: cysetuptest
Version: 0.11
Summary: first setup test
Home-page: http://pypi.python.org/pypi/cysetuptest/
Author: YuChen
Author-email: 14075840@qq.com
License: GPL
Keywords: firstsetuptest
Platform: Independant
